wmltools/__init__.py
wmltools-1.0.0.dist-info/licenses/LICENSE
wmltools-1.0.0.dist-info/WHEEL
wmltools-1.0.0.dist-info/METADATA
wmltools-1.0.0.dist-info/RECORD
