Metadata-Version: 2.4
Name: wmltools
Version: 1.0.0
Summary: A machine learning tools library
Author: wliafe
Author-email: wliafe <914099435@qq.com>
License-Expression: Apache-2.0
License-File: LICENSE
Classifier: Programming Language :: Python :: 3
Classifier: Operating System :: OS Independent
Requires-Dist: httpx>=0.28.1
Requires-Dist: ipython>=8.12.3
Requires-Dist: matplotlib>=3.7.5
Requires-Dist: pandas>=2.0.3
Requires-Dist: tqdm>=4.67.1
Requires-Python: >=3.8
Project-URL: Homepage, https://github.com/wliafe/mltools
Project-URL: Issues, https://github.com/wliafe/mltools/issues
